{
  "site_name": "Tellent Hiring Hub",
  "domain": "https://brightlane.github.io/tellent",
  "affiliate_url": "https://join.tellent.com/sjxu9svfbqoi",
  "pages": [
    {
      "slug": "index",
      "title": "Tellent ATS & Recruiting Software",
      "description": "Modern recruiting software and applicant tracking tools for growing teams.",
      "keyword": "tellent ats"
    },
    {
      "slug": "ai-recruiting",
      "title": "AI Recruiting Software",
      "description": "Automate hiring and recruitment workflows using AI recruiting tools.",
      "keyword": "ai recruiting software"
    },
    {
      "slug": "applicant-tracking-system",
      "title": "Best Applicant Tracking System",
      "description": "Discover how ATS platforms streamline hiring pipelines.",
      "keyword": "applicant tracking system"
    },
    {
      "slug": "recruitment-automation",
      "title": "Recruitment Automation Tools",
      "description": "Reduce manual hiring work using recruitment automation.",
      "keyword": "recruitment automation"
    },
    {
      "slug": "candidate-management",
      "title": "Candidate Management Software",
      "description": "Organize candidates and improve hiring collaboration.",
      "keyword": "candidate management software"
    },
    {
      "slug": "hiring-software",
      "title": "Best Hiring Software For Businesses",
      "description": "Top hiring platforms for startups, HR teams, and recruiters.",
      "keyword": "hiring software"
    },
    {
      "slug": "ats-for-startups",
      "title": "Best ATS For Startups",
      "description": "Affordable applicant tracking systems for startup hiring.",
      "keyword": "ats for startups"
    },
    {
      "slug": "recruiting-crm",
      "title": "Recruiting CRM Software",
      "description": "Manage recruiting pipelines and candidate relationships.",
      "keyword": "recruiting crm"
    }
  ],
  "industries": [
    "tech-companies",
    "staffing-agencies",
    "healthcare",
    "restaurants",
    "retail",
    "startups",
    "law-firms",
    "real-estate",
    "construction",
    "saas"
  ]
}